application_example/__init__.py
application_example/example.py
amoragon_test-0.1.0.dist-info/METADATA
amoragon_test-0.1.0.dist-info/WHEEL
amoragon_test-0.1.0.dist-info/top_level.txt
amoragon_test-0.1.0.dist-info/RECORD
