Metadata-Version: 2.1
Name: amoragon-test
Version: 0.1.0
Summary: Un ejemplo sencillo
Author: amoragon
Author-email: antonio.moragon@gmail.com
License: UNKNOWN
Platform: UNKNOWN
Requires-Python: >=3.6
Requires-Dist: build
Requires-Dist: twine
Requires-Dist: coloredlogs
